lib_pdsi/__init__.py
lib_pdsi/main.py
lib_pdsi/complex/__init__.py
lib_pdsi/complex/magnitude.py
lib_pdsi/complex/phase.py
lib_pdsi/dft/__init__.py
lib_pdsi/dft/dft.py
lib_pdsi/dft/versions/__init__.py
lib_pdsi/dft/versions/basis.py
lib_pdsi/dft/versions/fft.py
lib_pdsi/dft/versions/mtx.py
lib_pdsi/dft/versions/signal.py
lib_pdsi-0.1.0.dist-info/licenses/LICENSE
lib_pdsi-0.1.0.dist-info/METADATA
lib_pdsi-0.1.0.dist-info/WHEEL
lib_pdsi-0.1.0.dist-info/top_level.txt
lib_pdsi-0.1.0.dist-info/RECORD
