Metadata-Version: 2.4
Name: lib-pdsi
Version: 0.1.0
Summary: Biblioteca simples para uso na matéria de Processamento Digital de Sinais e Imagens
Author-email: Raphael Alves <rapha555lima@gmail.com>
License: MIT License
Project-URL: Homepage, https://github.com/phael-exe/lib_pdsi
Project-URL: Repository, https://github.com/phael-exe/lib_pdsi
Classifier: License :: OSI Approved :: MIT License
Classifier: Programming Language :: Python :: 3
Classifier: Operating System :: OS Independent
Requires-Python: >=3.12
License-File: LICENSE
Requires-Dist: matplotlib>=3.10.7
Requires-Dist: numpy>=2.3.3
Requires-Dist: pandas>=2.3.3
Requires-Dist: pytest>=8.4.2
Dynamic: license-file
